parameterparser/__init__.py
parameterparser/cluster.py
parameterparser/exception.py
parameterparser/parameter.py
parameterparser/parser.py
parameterparser/result.py
parameterparser/usage_style.py
parameterparser-0.1.7.dist-info/LICENSE
parameterparser-0.1.7.dist-info/METADATA
parameterparser-0.1.7.dist-info/WHEEL
parameterparser-0.1.7.dist-info/top_level.txt
parameterparser-0.1.7.dist-info/RECORD
