Metadata-Version: 2.1
Name: parameterparser
Version: 0.1.7
Summary: An advanced parameter parser for Python.
Home-page: https://github.com/nathan-fiscaletti/parameterparser-py
Author: Nathan Fiscaletti
Author-email: nathan.fiscaletti@gmail.com
License: UNKNOWN
Platform: UNKNOWN
Classifier: Programming Language :: Python :: 2.7
Classifier: Programming Language :: Python :: 3.7
Classifier: License :: OSI Approved :: MIT License
Classifier: Operating System :: OS Independent
